{
    "electron_shells": [
        {
            "function_type": "gto",
            "region": "",
            "angular_momentum": [
                0
            ],
            "exponents": [
                "2894.8325990",
                "435.41939120",
                "98.843328866",
                "27.485198001",
                "8.5405498171"
            ],
            "coefficients": [
                [
                    "-0.53408255515E-02",
                    "-0.39904258866E-01",
                    "-0.17912768038",
                    "-0.46758090825",
                    "-0.44653131020"
                ]
            ]
        },
        {
            "function_type": "gto",
            "region": "",
            "angular_momentum": [
                0
            ],
            "exponents": [
                "1.0654578038"
            ],
            "coefficients": [
                [
                    "1.0000000"
                ]
            ]
        },
        {
            "function_type": "gto",
            "region": "",
            "angular_momentum": [
                0
            ],
            "exponents": [
                "0.33247346748"
            ],
            "coefficients": [
                [
                    "1.0000000"
                ]
            ]
        },
        {
            "function_type": "gto",
            "region": "",
            "angular_momentum": [
                1
            ],
            "exponents": [
                "22.696633924",
                "4.9872339257",
                "1.3491613954"
            ],
            "coefficients": [
                [
                    "-0.45212874436E-01",
                    "-0.23754317067",
                    "-0.51287353587"
                ]
            ]
        },
        {
            "function_type": "gto",
            "region": "",
            "angular_momentum": [
                1
            ],
            "exponents": [
                "0.34829881977"
            ],
            "coefficients": [
                [
                    "1.0000000"
                ]
            ]
        },
        {
            "function_type": "gto_spherical",
            "region": "",
            "angular_momentum": [
                2
            ],
            "exponents": [
                "1.4000000"
            ],
            "coefficients": [
                [
                    "1.0000000"
                ]
            ]
        },
        {
            "function_type": "gto",
            "region": "",
            "angular_momentum": [
                0
            ],
            "exponents": [
                "0.98097752264E-01"
            ],
            "coefficients": [
                [
                    "1.0000000"
                ]
            ]
        },
        {
            "function_type": "gto",
            "region": "",
            "angular_momentum": [
                1
            ],
            "exponents": [
                "0.83372148304E-01"
            ],
            "coefficients": [
                [
                    "1.0000000"
                ]
            ]
        },
        {
            "function_type": "gto_spherical",
            "region": "",
            "angular_momentum": [
                2
            ],
            "exponents": [
                "0.22301361948"
            ],
            "coefficients": [
                [
                    "1.0000000"
                ]
            ]
        }
    ],
    "references": [
        {
            "reference_description": "Common base shells for def2-SV* basis sets",
            "reference_keys": [
                "weigend2005a"
            ]
        },
        {
            "reference_description": "Additional functions to form def2-SVPD",
            "reference_keys": [
                "rappoport2010a"
            ]
        }
    ]
}