{
    "electron_shells": [
        {
            "function_type": "gto",
            "region": "",
            "angular_momentum": [
                0
            ],
            "exponents": [
                "5.988000E+03",
                "8.989000E+02",
                "2.059000E+02",
                "5.924000E+01",
                "1.987000E+01",
                "7.406000E+00",
                "2.930000E+00",
                "1.189000E+00",
                "4.798000E-01",
                "7.509000E-02",
                "2.832000E-02"
            ],
            "coefficients": [
                [
                    "1.330000E-04",
                    "1.025000E-03",
                    "5.272000E-03",
                    "2.092900E-02",
                    "6.634000E-02",
                    "1.657750E-01",
                    "3.150380E-01",
                    "3.935230E-01",
                    "1.908700E-01",
                    "5.414000E-03",
                    "-1.328000E-03"
                ],
                [
                    "-2.100000E-05",
                    "-1.610000E-04",
                    "-8.200000E-04",
                    "-3.326000E-03",
                    "-1.051900E-02",
                    "-2.809700E-02",
                    "-5.593600E-02",
                    "-9.923700E-02",
                    "-1.121890E-01",
                    "5.678890E-01",
                    "5.303820E-01"
                ],
                [
                    "0.000000E+00",
                    "0.000000E+00",
                    "0.000000E+00",
                    "0.000000E+00",
                    "0.000000E+00",
                    "0.000000E+00",
                    "0.000000E+00",
                    "0.000000E+00",
                    "0.000000E+00",
                    "1.000000E+00",
                    "0.000000E+00"
                ],
                [
                    "0.000000E+00",
                    "0.000000E+00",
                    "0.000000E+00",
                    "0.000000E+00",
                    "0.000000E+00",
                    "0.000000E+00",
                    "0.000000E+00",
                    "0.000000E+00",
                    "0.000000E+00",
                    "0.000000E+00",
                    "1.000000E+00"
                ]
            ]
        },
        {
            "function_type": "gto",
            "region": "",
            "angular_momentum": [
                1
            ],
            "exponents": [
                "3.266000E+00",
                "6.511000E-01",
                "1.696000E-01",
                "5.578000E-02",
                "2.050000E-02"
            ],
            "coefficients": [
                [
                    "8.630000E-03",
                    "4.753800E-02",
                    "2.097720E-01",
                    "5.285220E-01",
                    "3.827440E-01"
                ],
                [
                    "0.000000E+00",
                    "0.000000E+00",
                    "0.000000E+00",
                    "1.000000E+00",
                    "0.000000E+00"
                ],
                [
                    "0.000000E+00",
                    "0.000000E+00",
                    "0.000000E+00",
                    "0.000000E+00",
                    "1.000000E+00"
                ]
            ]
        },
        {
            "function_type": "gto_spherical",
            "region": "",
            "angular_momentum": [
                2
            ],
            "exponents": [
                "1.900000E-01",
                "7.250000E-02"
            ],
            "coefficients": [
                [
                    "1.000000E+00",
                    "0.000000E+00"
                ],
                [
                    "0.000000E+00",
                    "1.000000E+00"
                ]
            ]
        },
        {
            "function_type": "gto_spherical",
            "region": "",
            "angular_momentum": [
                3
            ],
            "exponents": [
                "1.270000E-01"
            ],
            "coefficients": [
                [
                    "1.0000000"
                ]
            ]
        },
        {
            "function_type": "gto",
            "region": "",
            "angular_momentum": [
                0
            ],
            "exponents": [
                "7.600000E-03"
            ],
            "coefficients": [
                [
                    "1.000000E+00"
                ]
            ]
        },
        {
            "function_type": "gto",
            "region": "",
            "angular_momentum": [
                1
            ],
            "exponents": [
                "9.100000E-03"
            ],
            "coefficients": [
                [
                    "1.000000E+00"
                ]
            ]
        },
        {
            "function_type": "gto_spherical",
            "region": "",
            "angular_momentum": [
                2
            ],
            "exponents": [
                "4.280000E-02"
            ],
            "coefficients": [
                [
                    "1.000000E+00"
                ]
            ]
        },
        {
            "function_type": "gto_spherical",
            "region": "",
            "angular_momentum": [
                3
            ],
            "exponents": [
                "8.120000E-02"
            ],
            "coefficients": [
                [
                    "1.000000E+00"
                ]
            ]
        }
    ],
    "references": [
        {
            "reference_description": "Common functions for cc-pVTZ and similar",
            "reference_keys": [
                "prascher2011a"
            ]
        },
        {
            "reference_description": "Augmenting functions for cc-pVTZ",
            "reference_keys": [
                "prascher2011a"
            ]
        }
    ]
}