{
    "electron_shells": [
        {
            "function_type": "gto",
            "region": "",
            "angular_momentum": [
                0
            ],
            "exponents": [
                "26.077272000",
                "5.7127838000",
                "4.4057848000"
            ],
            "coefficients": [
                [
                    "0.23198684846E-02",
                    "-0.29787719611",
                    "0.70022722515"
                ]
            ]
        },
        {
            "function_type": "gto",
            "region": "",
            "angular_momentum": [
                0
            ],
            "exponents": [
                "2.1315325829"
            ],
            "coefficients": [
                [
                    "1.0000000"
                ]
            ]
        },
        {
            "function_type": "gto",
            "region": "",
            "angular_momentum": [
                0
            ],
            "exponents": [
                "0.49385808956"
            ],
            "coefficients": [
                [
                    "1.0000000"
                ]
            ]
        },
        {
            "function_type": "gto",
            "region": "",
            "angular_momentum": [
                0
            ],
            "exponents": [
                "0.23595687888"
            ],
            "coefficients": [
                [
                    "1.0000000"
                ]
            ]
        },
        {
            "function_type": "gto",
            "region": "",
            "angular_momentum": [
                0
            ],
            "exponents": [
                "0.63593489661E-01"
            ],
            "coefficients": [
                [
                    "1.0000000"
                ]
            ]
        },
        {
            "function_type": "gto",
            "region": "",
            "angular_momentum": [
                0
            ],
            "exponents": [
                "0.31545394754E-01"
            ],
            "coefficients": [
                [
                    "1.0000000"
                ]
            ]
        },
        {
            "function_type": "gto",
            "region": "",
            "angular_momentum": [
                0
            ],
            "exponents": [
                "0.15777655296E-01"
            ],
            "coefficients": [
                [
                    "1.0000000"
                ]
            ]
        },
        {
            "function_type": "gto",
            "region": "",
            "angular_momentum": [
                1
            ],
            "exponents": [
                "6.0000000000",
                "3.6808191615",
                "2.3265462081",
                "0.64342629633"
            ],
            "coefficients": [
                [
                    "-0.11397960924E-01",
                    "0.14675038550",
                    "-0.35581819167",
                    "0.45834955229"
                ]
            ]
        },
        {
            "function_type": "gto",
            "region": "",
            "angular_momentum": [
                1
            ],
            "exponents": [
                "0.33584281962"
            ],
            "coefficients": [
                [
                    "1.0000000"
                ]
            ]
        },
        {
            "function_type": "gto",
            "region": "",
            "angular_momentum": [
                1
            ],
            "exponents": [
                "0.16519051916"
            ],
            "coefficients": [
                [
                    "1.0000000"
                ]
            ]
        },
        {
            "function_type": "gto",
            "region": "",
            "angular_momentum": [
                1
            ],
            "exponents": [
                "0.56715971797E-01"
            ],
            "coefficients": [
                [
                    "1.0000000"
                ]
            ]
        },
        {
            "function_type": "gto",
            "region": "",
            "angular_momentum": [
                1
            ],
            "exponents": [
                "0.22100824776E-01"
            ],
            "coefficients": [
                [
                    "1.0000000"
                ]
            ]
        },
        {
            "function_type": "gto_spherical",
            "region": "",
            "angular_momentum": [
                2
            ],
            "exponents": [
                "1.2000000000",
                "1.0239524401",
                "0.37508490282"
            ],
            "coefficients": [
                [
                    "-0.35803482414",
                    "0.40483734122",
                    "0.37649639849"
                ]
            ]
        },
        {
            "function_type": "gto_spherical",
            "region": "",
            "angular_momentum": [
                2
            ],
            "exponents": [
                "0.17161940245"
            ],
            "coefficients": [
                [
                    "1.0000000"
                ]
            ]
        },
        {
            "function_type": "gto_spherical",
            "region": "",
            "angular_momentum": [
                2
            ],
            "exponents": [
                "0.78780423402E-01"
            ],
            "coefficients": [
                [
                    "1.0000000"
                ]
            ]
        },
        {
            "function_type": "gto_spherical",
            "region": "",
            "angular_momentum": [
                2
            ],
            "exponents": [
                "0.35000047794E-01"
            ],
            "coefficients": [
                [
                    "1.0000000"
                ]
            ]
        },
        {
            "function_type": "gto_spherical",
            "region": "",
            "angular_momentum": [
                3
            ],
            "exponents": [
                "0.6558000"
            ],
            "coefficients": [
                [
                    "1.0000000"
                ]
            ]
        },
        {
            "function_type": "gto_spherical",
            "region": "",
            "angular_momentum": [
                3
            ],
            "exponents": [
                "0.2568300"
            ],
            "coefficients": [
                [
                    "1.0000000"
                ]
            ]
        },
        {
            "function_type": "gto_spherical",
            "region": "",
            "angular_momentum": [
                3
            ],
            "exponents": [
                "0.1005800"
            ],
            "coefficients": [
                [
                    "1.0000000"
                ]
            ]
        },
        {
            "function_type": "gto_spherical",
            "region": "",
            "angular_momentum": [
                4
            ],
            "exponents": [
                "0.1790700"
            ],
            "coefficients": [
                [
                    "1.0000000"
                ]
            ]
        }
    ],
    "references": [
        {
            "reference_description": "Common base shells for def2-QZV*",
            "reference_keys": [
                "weigend2005a"
            ]
        },
        {
            "reference_description": "Additional functions to form def2-QZVP",
            "reference_keys": [
                "weigend2005a"
            ]
        },
        {
            "reference_description": "ECP basis set for Ahlrichs def2",
            "reference_keys": [
                "dolg1989a",
                "dolg1993b"
            ]
        }
    ],
    "ecp_potentials": [
        {
            "angular_momentum": [
                3
            ],
            "coefficients": [
                [
                    "-36.0100160"
                ]
            ],
            "ecp_type": "scalar_ecp",
            "r_exponents": [
                2
            ],
            "gaussian_exponents": [
                "4.0286000"
            ]
        },
        {
            "angular_momentum": [
                0
            ],
            "coefficients": [
                [
                    "91.9321770",
                    "-3.7887640",
                    "36.0100160"
                ]
            ],
            "ecp_type": "scalar_ecp",
            "r_exponents": [
                2,
                2,
                2
            ],
            "gaussian_exponents": [
                "3.3099000",
                "1.6550000",
                "4.0286000"
            ]
        },
        {
            "angular_momentum": [
                1
            ],
            "coefficients": [
                [
                    "63.7594860",
                    "-0.6479580",
                    "36.0100160"
                ]
            ],
            "ecp_type": "scalar_ecp",
            "r_exponents": [
                2,
                2,
                2
            ],
            "gaussian_exponents": [
                "2.8368000",
                "1.4184000",
                "4.0286000"
            ]
        },
        {
            "angular_momentum": [
                2
            ],
            "coefficients": [
                [
                    "36.1161730",
                    "0.2191140",
                    "36.0100160"
                ]
            ],
            "ecp_type": "scalar_ecp",
            "r_exponents": [
                2,
                2,
                2
            ],
            "gaussian_exponents": [
                "2.0213000",
                "1.0107000",
                "4.0286000"
            ]
        }
    ], 
    "ecp_electrons": 46
}