{
    "electron_shells": [
        {
            "function_type": "gto",
            "region": "",
            "angular_momentum": [
                0
            ],
            "exponents": [
                "5.7000000000",
                "5.2043612469"
            ],
            "coefficients": [
                [
                    "1.3292982002",
                    "-1.7367497134"
                ]
            ]
        },
        {
            "function_type": "gto",
            "region": "",
            "angular_momentum": [
                0
            ],
            "exponents": [
                "2.1475437282"
            ],
            "coefficients": [
                [
                    "1.0000000"
                ]
            ]
        },
        {
            "function_type": "gto",
            "region": "",
            "angular_momentum": [
                0
            ],
            "exponents": [
                "0.41033660537"
            ],
            "coefficients": [
                [
                    "1.0000000"
                ]
            ]
        },
        {
            "function_type": "gto",
            "region": "",
            "angular_momentum": [
                0
            ],
            "exponents": [
                "0.18393532770"
            ],
            "coefficients": [
                [
                    "1.0000000"
                ]
            ]
        },
        {
            "function_type": "gto",
            "region": "",
            "angular_momentum": [
                0
            ],
            "exponents": [
                "0.72521216545E-01"
            ],
            "coefficients": [
                [
                    "1.0000000"
                ]
            ]
        },
        {
            "function_type": "gto",
            "region": "",
            "angular_momentum": [
                0
            ],
            "exponents": [
                "0.34526334903E-01"
            ],
            "coefficients": [
                [
                    "1.0000000"
                ]
            ]
        },
        {
            "function_type": "gto",
            "region": "",
            "angular_momentum": [
                0
            ],
            "exponents": [
                "0.16157891872E-01"
            ],
            "coefficients": [
                [
                    "1.0000000"
                ]
            ]
        },
        {
            "function_type": "gto",
            "region": "",
            "angular_momentum": [
                1
            ],
            "exponents": [
                "5.6000000000",
                "5.1104879274",
                "2.5006544803",
                "0.51947995345"
            ],
            "coefficients": [
                [
                    "0.51385026013",
                    "-0.70529238864",
                    "0.42822329830",
                    "-0.57125984472"
                ]
            ]
        },
        {
            "function_type": "gto",
            "region": "",
            "angular_momentum": [
                1
            ],
            "exponents": [
                "0.24536994841"
            ],
            "coefficients": [
                [
                    "1.0000000"
                ]
            ]
        },
        {
            "function_type": "gto",
            "region": "",
            "angular_momentum": [
                1
            ],
            "exponents": [
                "0.11256056700"
            ],
            "coefficients": [
                [
                    "1.0000000"
                ]
            ]
        },
        {
            "function_type": "gto",
            "region": "",
            "angular_momentum": [
                1
            ],
            "exponents": [
                "0.34917622027E-01"
            ],
            "coefficients": [
                [
                    "1.0000000"
                ]
            ]
        },
        {
            "function_type": "gto",
            "region": "",
            "angular_momentum": [
                1
            ],
            "exponents": [
                "0.16320065666E-01"
            ],
            "coefficients": [
                [
                    "1.0000000"
                ]
            ]
        },
        {
            "function_type": "gto_spherical",
            "region": "",
            "angular_momentum": [
                2
            ],
            "exponents": [
                "2.7000000000",
                "2.3460740881",
                "0.39553542609"
            ],
            "coefficients": [
                [
                    ".14372069823827",
                    "-.19565347309413",
                    ".29963058551591"
                ]
            ]
        },
        {
            "function_type": "gto_spherical",
            "region": "",
            "angular_momentum": [
                2
            ],
            "exponents": [
                "0.12967935859"
            ],
            "coefficients": [
                [
                    "1.0000000"
                ]
            ]
        },
        {
            "function_type": "gto_spherical",
            "region": "",
            "angular_momentum": [
                2
            ],
            "exponents": [
                "0.40463066544E-01"
            ],
            "coefficients": [
                [
                    "1.0000000"
                ]
            ]
        },
        {
            "function_type": "gto_spherical",
            "region": "",
            "angular_momentum": [
                3
            ],
            "exponents": [
                "10.00",
                "3.20",
                "1.00",
                "0.32"
            ],
            "coefficients": [
                [
                    "0.073",
                    "0.210",
                    "0.350",
                    "0.360"
                ]
            ]
        },
        {
            "function_type": "gto_spherical",
            "region": "",
            "angular_momentum": [
                3
            ],
            "exponents": [
                ".08788"
            ],
            "coefficients": [
                [
                    "1.0000000"
                ]
            ]
        },
        {
            "function_type": "gto_spherical",
            "region": "",
            "angular_momentum": [
                4
            ],
            "exponents": [
                ".5"
            ],
            "coefficients": [
                [
                    "1.0000000"
                ]
            ]
        }
    ],
    "references": [
        {
            "reference_description": "Common base shells for def2-QZV*",
            "reference_keys": [
                "weigend2005a"
            ]
        },
        {
            "reference_description": "ECP basis set for Ahlrichs def2",
            "reference_keys": [
                "kaupp1991a"
            ]
        }
    ],
    "ecp_potentials": [
        {
            "angular_momentum": [
                3
            ],
            "coefficients": [
                [
                    "-33.4731740"
                ]
            ],
            "ecp_type": "scalar_ecp",
            "r_exponents": [
                2
            ],
            "gaussian_exponents": [
                "3.5894650"
            ]
        },
        {
            "angular_momentum": [
                0
            ],
            "coefficients": [
                [
                    "427.8458160",
                    "204.4175300",
                    "33.4731740"
                ]
            ],
            "ecp_type": "scalar_ecp",
            "r_exponents": [
                2,
                2,
                2
            ],
            "gaussian_exponents": [
                "9.5269860",
                "4.4875100",
                "3.5894650"
            ]
        },
        {
            "angular_momentum": [
                1
            ],
            "coefficients": [
                [
                    "293.6058640",
                    "294.1933160",
                    "33.4731740"
                ]
            ],
            "ecp_type": "scalar_ecp",
            "r_exponents": [
                2,
                2,
                2
            ],
            "gaussian_exponents": [
                "8.3159300",
                "4.2922170",
                "3.5894650"
            ]
        },
        {
            "angular_momentum": [
                2
            ],
            "coefficients": [
                [
                    "112.5504020",
                    "181.7826210",
                    "33.4731740"
                ]
            ],
            "ecp_type": "scalar_ecp",
            "r_exponents": [
                2,
                2,
                2
            ],
            "gaussian_exponents": [
                "5.9161080",
                "2.8748420",
                "3.5894650"
            ]
        }
    ], 
    "ecp_electrons": 46
}