{
    "electron_shells": [
        {
            "function_type": "gto",
            "region": "",
            "angular_momentum": [
                0
            ],
            "exponents": [
                "15.000000000",
                "12.910581694"
            ],
            "coefficients": [
                [
                    "-0.19945408941",
                    "0.33689922245"
                ]
            ]
        },
        {
            "function_type": "gto",
            "region": "",
            "angular_momentum": [
                0
            ],
            "exponents": [
                "4.4493321158"
            ],
            "coefficients": [
                [
                    "1.0000000"
                ]
            ]
        },
        {
            "function_type": "gto",
            "region": "",
            "angular_momentum": [
                0
            ],
            "exponents": [
                "1.0548409451"
            ],
            "coefficients": [
                [
                    "1.0000000"
                ]
            ]
        },
        {
            "function_type": "gto",
            "region": "",
            "angular_momentum": [
                0
            ],
            "exponents": [
                "0.47909677246"
            ],
            "coefficients": [
                [
                    "1.0000000"
                ]
            ]
        },
        {
            "function_type": "gto",
            "region": "",
            "angular_momentum": [
                0
            ],
            "exponents": [
                "0.99124162989E-01"
            ],
            "coefficients": [
                [
                    "1.0000000"
                ]
            ]
        },
        {
            "function_type": "gto",
            "region": "",
            "angular_momentum": [
                0
            ],
            "exponents": [
                "0.36882799789E-01"
            ],
            "coefficients": [
                [
                    "1.0000000"
                ]
            ]
        },
        {
            "function_type": "gto",
            "region": "",
            "angular_momentum": [
                1
            ],
            "exponents": [
                "10.027138011",
                "5.8463419741",
                "1.4968345491",
                "0.72934632066"
            ],
            "coefficients": [
                [
                    "0.61481602710E-01",
                    "-0.23600729385",
                    "0.47746483995",
                    "0.50731543496"
                ]
            ]
        },
        {
            "function_type": "gto",
            "region": "",
            "angular_momentum": [
                1
            ],
            "exponents": [
                "0.33913558879"
            ],
            "coefficients": [
                [
                    "1.0000000"
                ]
            ]
        },
        {
            "function_type": "gto",
            "region": "",
            "angular_momentum": [
                1
            ],
            "exponents": [
                "0.11000000000"
            ],
            "coefficients": [
                [
                    "1.0000000"
                ]
            ]
        },
        {
            "function_type": "gto",
            "region": "",
            "angular_momentum": [
                1
            ],
            "exponents": [
                "0.35000000000E-01"
            ],
            "coefficients": [
                [
                    "1.0000000"
                ]
            ]
        },
        {
            "function_type": "gto_spherical",
            "region": "",
            "angular_momentum": [
                2
            ],
            "exponents": [
                "5.0906268699",
                "2.0156178510",
                "0.88113887240"
            ],
            "coefficients": [
                [
                    "-0.32176405405E-01",
                    "0.21280802536",
                    "0.44403309175"
                ]
            ]
        },
        {
            "function_type": "gto_spherical",
            "region": "",
            "angular_momentum": [
                2
            ],
            "exponents": [
                "0.36427094833"
            ],
            "coefficients": [
                [
                    "1.0000000"
                ]
            ]
        },
        {
            "function_type": "gto_spherical",
            "region": "",
            "angular_momentum": [
                2
            ],
            "exponents": [
                "0.13678402297"
            ],
            "coefficients": [
                [
                    "1.0000000"
                ]
            ]
        },
        {
            "function_type": "gto_spherical",
            "region": "",
            "angular_momentum": [
                3
            ],
            "exponents": [
                "0.7908500"
            ],
            "coefficients": [
                [
                    "1.0000000"
                ]
            ]
        }
    ],
    "references": [
        {
            "reference_description": "Common base shells for def2-TZV*",
            "reference_keys": [
                "weigend2005a"
            ]
        },
        {
            "reference_description": "Additional functions to form def2-TZVP",
            "reference_keys": [
                "weigend2005a"
            ]
        },
        {
            "reference_description": "ECP basis set for Ahlrichs def2",
            "reference_keys": [
                "andrae1990a"
            ]
        }
    ],
    "ecp_potentials": [
        {
            "angular_momentum": [
                3
            ],
            "coefficients": [
                [
                    "-26.56244747",
                    "-4.58568054"
                ]
            ],
            "ecp_type": "scalar_ecp",
            "r_exponents": [
                2,
                2
            ],
            "gaussian_exponents": [
                "10.4000000",
                "5.2000000"
            ]
        },
        {
            "angular_momentum": [
                0
            ],
            "coefficients": [
                [
                    "195.15916591",
                    "28.09260333",
                    "26.56244747",
                    "4.58568054"
                ]
            ],
            "ecp_type": "scalar_ecp",
            "r_exponents": [
                2,
                2,
                2,
                2
            ],
            "gaussian_exponents": [
                "10.4223462",
                "5.0365160",
                "10.4000000",
                "5.2000000"
            ]
        },
        {
            "angular_momentum": [
                1
            ],
            "coefficients": [
                [
                    "135.28456622",
                    "21.80650430",
                    "26.56244747",
                    "4.58568054"
                ]
            ],
            "ecp_type": "scalar_ecp",
            "r_exponents": [
                2,
                2,
                2,
                2
            ],
            "gaussian_exponents": [
                "8.9504494",
                "4.8544394",
                "10.4000000",
                "5.2000000"
            ]
        },
        {
            "angular_momentum": [
                2
            ],
            "coefficients": [
                [
                    "54.32972942",
                    "11.15506795",
                    "26.56244747",
                    "4.58568054"
                ]
            ],
            "ecp_type": "scalar_ecp",
            "r_exponents": [
                2,
                2,
                2,
                2
            ],
            "gaussian_exponents": [
                "6.9456968",
                "3.9705849",
                "10.4000000",
                "5.2000000"
            ]
        }
    ], 
    "ecp_electrons": 28
}