{
    "electron_shells": [
        {
            "function_type": "gto",
            "region": "",
            "angular_momentum": [
                0
            ],
            "exponents": [
                "1.610300E+08",
                "2.875580E+07",
                "6.423240E+06",
                "1.721200E+06",
                "5.339940E+05",
                "1.861940E+05",
                "7.120170E+04",
                "2.927620E+04",
                "1.274230E+04",
                "5.800510E+03",
                "2.736960E+03",
                "1.329990E+03",
                "6.626110E+02",
                "3.374150E+02",
                "1.752340E+02",
                "9.264340E+01",
                "4.975760E+01",
                "2.707280E+01",
                "1.486100E+01",
                "8.181210E+00",
                "4.479410E+00",
                "2.411910E+00",
                "1.258440E+00",
                "6.312340E-01",
                "2.152970E-01",
                "1.185100E-01",
                "5.720900E-02",
                "2.716600E-02"
            ],
            "coefficients": [
                [
                    "8.662183E-08",
                    "5.771763E-07",
                    "3.338777E-06",
                    "1.525639E-05",
                    "5.896429E-05",
                    "1.992702E-04",
                    "6.077789E-04",
                    "1.710961E-03",
                    "4.517474E-03",
                    "1.127782E-02",
                    "2.661227E-02",
                    "5.860637E-02",
                    "1.169482E-01",
                    "1.999746E-01",
                    "2.643784E-01",
                    "2.249341E-01",
                    "9.906240E-02",
                    "5.071482E-02",
                    "8.902685E-02",
                    "7.586152E-02",
                    "2.214222E-02",
                    "1.717531E-03",
                    "-5.409407E-06",
                    "-6.718433E-05",
                    "-7.178600E-07",
                    "6.032560E-06",
                    "6.126313E-06",
                    "2.509112E-06"
                ],
                [
                    "-4.556183E-08",
                    "-3.035847E-07",
                    "-1.756166E-06",
                    "-8.024821E-06",
                    "-3.101768E-05",
                    "-1.048428E-04",
                    "-3.199314E-04",
                    "-9.016105E-04",
                    "-2.386390E-03",
                    "-5.988100E-03",
                    "-1.428063E-02",
                    "-3.211732E-02",
                    "-6.678496E-02",
                    "-1.236623E-01",
                    "-1.908018E-01",
                    "-2.115468E-01",
                    "-9.922228E-02",
                    "1.722946E-01",
                    "4.619215E-01",
                    "3.996247E-01",
                    "1.162798E-01",
                    "8.604498E-03",
                    "-1.265293E-03",
                    "-7.648586E-04",
                    "-6.404352E-05",
                    "6.372632E-05",
                    "1.662965E-05",
                    "1.570013E-05"
                ],
                [
                    "1.041562E-08",
                    "6.941461E-08",
                    "4.014470E-07",
                    "1.835009E-06",
                    "7.090429E-06",
                    "2.398084E-05",
                    "7.316286E-05",
                    "2.064944E-04",
                    "5.470930E-04",
                    "1.379359E-03",
                    "3.311503E-03",
                    "7.570774E-03",
                    "1.617381E-02",
                    "3.158299E-02",
                    "5.307111E-02",
                    "6.689319E-02",
                    "3.338852E-02",
                    "-8.553213E-02",
                    "-2.983211E-01",
                    "-3.720681E-01",
                    "-3.313281E-02",
                    "4.476713E-01",
                    "5.711223E-01",
                    "2.346370E-01",
                    "1.505834E-02",
                    "-3.444353E-03",
                    "3.212369E-03",
                    "1.675018E-04"
                ],
                [
                    "-2.200797E-09",
                    "-1.466850E-08",
                    "-8.482259E-08",
                    "-3.877784E-07",
                    "-1.498105E-06",
                    "-5.067913E-06",
                    "-1.545763E-05",
                    "-4.364220E-05",
                    "-1.155867E-04",
                    "-2.915733E-04",
                    "-6.997388E-04",
                    "-1.601143E-03",
                    "-3.420234E-03",
                    "-6.691847E-03",
                    "-1.125825E-02",
                    "-1.427562E-02",
                    "-7.134768E-03",
                    "1.848341E-02",
                    "6.724484E-02",
                    "8.704356E-02",
                    "4.998014E-03",
                    "-1.238556E-01",
                    "-1.989520E-01",
                    "-1.759940E-01",
                    "7.944520E-02",
                    "4.024933E-01",
                    "5.034063E-01",
                    "1.730481E-01"
                ],
                [
                    "-4.305752E-09",
                    "-2.848385E-08",
                    "-1.662977E-07",
                    "-7.515459E-07",
                    "-2.944684E-06",
                    "-9.789564E-06",
                    "-3.050378E-05",
                    "-8.391909E-05",
                    "-2.292077E-04",
                    "-5.578224E-04",
                    "-1.395052E-03",
                    "-3.045922E-03",
                    "-6.873444E-03",
                    "-1.259770E-02",
                    "-2.314866E-02",
                    "-2.548397E-02",
                    "-1.958046E-02",
                    "4.772897E-02",
                    "1.149297E-01",
                    "2.257042E-01",
                    "-6.554148E-02",
                    "-2.493425E-01",
                    "-6.686389E-01",
                    "2.041108E-01",
                    "1.227907E+00",
                    "1.857518E-01",
                    "-4.763281E-01",
                    "-6.704814E-01"
                ],
                [
                    "-7.600240E-09",
                    "-5.006064E-08",
                    "-2.938904E-07",
                    "-1.319357E-06",
                    "-5.211710E-06",
                    "-1.715261E-05",
                    "-5.410968E-05",
                    "-1.466455E-04",
                    "-4.077240E-04",
                    "-9.719138E-04",
                    "-2.489639E-03",
                    "-5.291021E-03",
                    "-1.233031E-02",
                    "-2.177919E-02",
                    "-4.215306E-02",
                    "-4.281763E-02",
                    "-4.064818E-02",
                    "9.666274E-02",
                    "1.952451E-01",
                    "5.139452E-01",
                    "-2.545005E-01",
                    "-9.219539E-01",
                    "-1.008643E+00",
                    "2.264662E+00",
                    "5.803464E-01",
                    "-2.105359E+00",
                    "8.909444E-02",
                    "9.625762E-01"
                ],
                [
                    "9.197016E-09",
                    "6.187033E-08",
                    "3.535327E-07",
                    "1.639554E-06",
                    "6.223594E-06",
                    "2.151491E-05",
                    "6.389719E-05",
                    "1.863210E-04",
                    "4.749694E-04",
                    "1.252974E-03",
                    "2.859209E-03",
                    "6.940624E-03",
                    "1.389573E-02",
                    "2.959972E-02",
                    "4.516314E-02",
                    "6.841808E-02",
                    "1.839713E-02",
                    "-5.186229E-02",
                    "-3.974522E-01",
                    "-6.606775E-01",
                    "5.215581E-01",
                    "2.838146E+00",
                    "-2.970658E+00",
                    "-8.507557E-01",
                    "4.245559E+00",
                    "-2.937293E+00",
                    "-1.140954E+00",
                    "1.438165E+00"
                ],
                [
                    "-1.070534E-08",
                    "-7.038714E-08",
                    "-4.141923E-07",
                    "-1.854049E-06",
                    "-7.350041E-06",
                    "-2.408411E-05",
                    "-7.638731E-05",
                    "-2.056945E-04",
                    "-5.763721E-04",
                    "-1.362515E-03",
                    "-3.527424E-03",
                    "-7.424293E-03",
                    "-1.758255E-02",
                    "-3.075095E-02",
                    "-6.133217E-02",
                    "-6.129559E-02",
                    "-6.543693E-02",
                    "1.523938E-01",
                    "3.484988E-01",
                    "1.604400E+00",
                    "-3.274465E+00",
                    "-1.449252E+00",
                    "7.547170E+00",
                    "-6.991470E+00",
                    "3.155202E+00",
                    "9.784141E-01",
                    "-3.643364E+00",
                    "1.948103E+00"
                ],
                [
                    "0.000000E+00",
                    "0.000000E+00",
                    "0.000000E+00",
                    "0.000000E+00",
                    "0.000000E+00",
                    "0.000000E+00",
                    "0.000000E+00",
                    "0.000000E+00",
                    "0.000000E+00",
                    "0.000000E+00",
                    "0.000000E+00",
                    "0.000000E+00",
                    "0.000000E+00",
                    "0.000000E+00",
                    "0.000000E+00",
                    "0.000000E+00",
                    "0.000000E+00",
                    "0.000000E+00",
                    "0.000000E+00",
                    "0.000000E+00",
                    "0.000000E+00",
                    "0.000000E+00",
                    "0.000000E+00",
                    "0.000000E+00",
                    "0.000000E+00",
                    "0.000000E+00",
                    "0.000000E+00",
                    "1.000000E+00"
                ]
            ]
        },
        {
            "function_type": "gto",
            "region": "",
            "angular_momentum": [
                1
            ],
            "exponents": [
                "9.751260E+04",
                "2.381510E+04",
                "7.540430E+03",
                "2.854080E+03",
                "1.217690E+03",
                "5.625150E+02",
                "2.742740E+02",
                "1.391140E+02",
                "7.285980E+01",
                "3.924480E+01",
                "2.164300E+01",
                "1.211490E+01",
                "6.769120E+00",
                "3.705280E+00",
                "1.979010E+00",
                "1.031270E+00",
                "5.136090E-01",
                "2.042640E-01",
                "8.387800E-02",
                "3.414200E-02"
            ],
            "coefficients": [
                [
                    "2.000000E-06",
                    "2.100000E-05",
                    "1.300000E-04",
                    "6.050000E-04",
                    "2.331000E-03",
                    "7.807000E-03",
                    "2.308900E-02",
                    "5.990800E-02",
                    "1.311200E-01",
                    "2.283230E-01",
                    "3.033890E-01",
                    "2.735320E-01",
                    "1.339910E-01",
                    "2.551600E-02",
                    "-6.900000E-04",
                    "-1.861000E-03",
                    "-7.880000E-04",
                    "-4.800000E-05",
                    "-2.000000E-06",
                    "0.000000E+00"
                ],
                [
                    "-1.000000E-06",
                    "-7.000000E-06",
                    "-4.600000E-05",
                    "-2.150000E-04",
                    "-8.320000E-04",
                    "-2.801000E-03",
                    "-8.373000E-03",
                    "-2.216000E-02",
                    "-5.004300E-02",
                    "-9.050200E-02",
                    "-1.266680E-01",
                    "-1.113190E-01",
                    "3.270500E-02",
                    "2.641890E-01",
                    "4.016030E-01",
                    "3.244220E-01",
                    "1.213180E-01",
                    "1.081500E-02",
                    "-2.510000E-04",
                    "2.270000E-04"
                ],
                [
                    "0.000000E+00",
                    "2.000000E-06",
                    "1.000000E-05",
                    "4.700000E-05",
                    "1.850000E-04",
                    "6.130000E-04",
                    "1.860000E-03",
                    "4.864000E-03",
                    "1.117500E-02",
                    "1.991100E-02",
                    "2.880900E-02",
                    "2.409000E-02",
                    "-8.661000E-03",
                    "-7.295300E-02",
                    "-1.066760E-01",
                    "-1.079120E-01",
                    "3.961500E-02",
                    "3.560400E-01",
                    "5.249090E-01",
                    "2.308960E-01"
                ],
                [
                    "0.000000E+00",
                    "3.000000E-06",
                    "1.600000E-05",
                    "7.300000E-05",
                    "2.900000E-04",
                    "9.510000E-04",
                    "2.922000E-03",
                    "7.536000E-03",
                    "1.756600E-02",
                    "3.077000E-02",
                    "4.585400E-02",
                    "3.678900E-02",
                    "-1.078600E-02",
                    "-1.231490E-01",
                    "-1.705170E-01",
                    "-1.595630E-01",
                    "1.356510E-01",
                    "6.254930E-01",
                    "3.770670E-01",
                    "1.619900E-02"
                ],
                [
                    "1.000000E-06",
                    "5.000000E-06",
                    "3.500000E-05",
                    "1.480000E-04",
                    "6.340000E-04",
                    "1.935000E-03",
                    "6.383000E-03",
                    "1.534000E-02",
                    "3.865400E-02",
                    "6.150600E-02",
                    "1.063540E-01",
                    "7.265900E-02",
                    "2.670000E-04",
                    "-4.227860E-01",
                    "-4.236170E-01",
                    "6.119600E-02",
                    "1.141035E+00",
                    "-7.076800E-02",
                    "-7.197110E-01",
                    "-1.851500E-02"
                ],
                [
                    "1.000000E-06",
                    "8.000000E-06",
                    "3.800000E-05",
                    "2.170000E-04",
                    "6.900000E-04",
                    "2.826000E-03",
                    "6.983000E-03",
                    "2.254100E-02",
                    "4.133500E-02",
                    "9.648600E-02",
                    "9.631100E-02",
                    "2.187580E-01",
                    "-1.991620E-01",
                    "-7.578960E-01",
                    "-4.881940E-01",
                    "2.065654E+00",
                    "-6.901820E-01",
                    "-1.206482E+00",
                    "1.063578E+00",
                    "4.061500E-02"
                ],
                [
                    "1.000000E-06",
                    "1.100000E-05",
                    "5.400000E-05",
                    "3.070000E-04",
                    "9.720000E-04",
                    "4.005000E-03",
                    "9.911000E-03",
                    "3.230300E-02",
                    "5.947300E-02",
                    "1.408890E-01",
                    "1.393220E-01",
                    "4.563840E-01",
                    "-9.863130E-01",
                    "-1.400931E+00",
                    "2.828169E+00",
                    "-4.544190E-01",
                    "-1.926268E+00",
                    "2.085117E+00",
                    "-9.653770E-01",
                    "-1.077040E-01"
                ],
                [
                    "0.000000E+00",
                    "0.000000E+00",
                    "0.000000E+00",
                    "0.000000E+00",
                    "0.000000E+00",
                    "0.000000E+00",
                    "0.000000E+00",
                    "0.000000E+00",
                    "0.000000E+00",
                    "0.000000E+00",
                    "0.000000E+00",
                    "0.000000E+00",
                    "0.000000E+00",
                    "0.000000E+00",
                    "0.000000E+00",
                    "0.000000E+00",
                    "0.000000E+00",
                    "0.000000E+00",
                    "0.000000E+00",
                    "1.000000E+00"
                ]
            ]
        },
        {
            "function_type": "gto_spherical",
            "region": "",
            "angular_momentum": [
                2
            ],
            "exponents": [
                "4.952480E+02",
                "1.490380E+02",
                "5.787280E+01",
                "2.537960E+01",
                "1.185940E+01",
                "5.796300E+00",
                "2.872750E+00",
                "1.407836E+00",
                "6.724070E-01",
                "3.088350E-01",
                "1.342970E-01",
                "5.361900E-02"
            ],
            "coefficients": [
                [
                    "1.950000E-04",
                    "1.820000E-03",
                    "9.860000E-03",
                    "3.541700E-02",
                    "9.488200E-02",
                    "1.886510E-01",
                    "2.703950E-01",
                    "2.963470E-01",
                    "2.565590E-01",
                    "1.640550E-01",
                    "6.056700E-02",
                    "6.043000E-03"
                ],
                [
                    "-2.260000E-04",
                    "-2.117000E-03",
                    "-1.150600E-02",
                    "-4.167300E-02",
                    "-1.148500E-01",
                    "-2.300360E-01",
                    "-2.787220E-01",
                    "-1.090440E-01",
                    "2.309180E-01",
                    "4.341780E-01",
                    "3.146810E-01",
                    "5.602600E-02"
                ],
                [
                    "2.980000E-04",
                    "2.841000E-03",
                    "1.538000E-02",
                    "5.693200E-02",
                    "1.620180E-01",
                    "3.251240E-01",
                    "2.071440E-01",
                    "-3.687400E-01",
                    "-5.808490E-01",
                    "1.267060E-01",
                    "5.876060E-01",
                    "1.462790E-01"
                ],
                [
                    "-4.190000E-04",
                    "-4.079000E-03",
                    "-2.189500E-02",
                    "-8.303100E-02",
                    "-2.568910E-01",
                    "-5.037510E-01",
                    "3.497610E-01",
                    "9.348700E-01",
                    "-6.383940E-01",
                    "-6.372560E-01",
                    "6.254560E-01",
                    "2.138350E-01"
                ],
                [
                    "-6.500000E-04",
                    "-4.633000E-03",
                    "-3.251900E-02",
                    "-1.010780E-01",
                    "-4.650190E-01",
                    "-3.186010E-01",
                    "1.514991E+00",
                    "-7.612670E-01",
                    "-9.671680E-01",
                    "1.443330E+00",
                    "-4.742000E-01",
                    "-3.586160E-01"
                ],
                [
                    "0.000000E+00",
                    "0.000000E+00",
                    "0.000000E+00",
                    "0.000000E+00",
                    "0.000000E+00",
                    "0.000000E+00",
                    "0.000000E+00",
                    "0.000000E+00",
                    "0.000000E+00",
                    "0.000000E+00",
                    "0.000000E+00",
                    "1.000000E+00"
                ]
            ]
        },
        {
            "function_type": "gto_spherical",
            "region": "",
            "angular_momentum": [
                3
            ],
            "exponents": [
                "8.592000E+00",
                "3.018700E+00",
                "1.060600E+00",
                "3.726000E-01"
            ],
            "coefficients": [
                [
                    "1.000000E+00",
                    "0.000000E+00",
                    "0.000000E+00",
                    "0.000000E+00"
                ],
                [
                    "0.000000E+00",
                    "1.000000E+00",
                    "0.000000E+00",
                    "0.000000E+00"
                ],
                [
                    "0.000000E+00",
                    "0.000000E+00",
                    "1.000000E+00",
                    "0.000000E+00"
                ],
                [
                    "0.000000E+00",
                    "0.000000E+00",
                    "0.000000E+00",
                    "1.000000E+00"
                ]
            ]
        },
        {
            "function_type": "gto_spherical",
            "region": "",
            "angular_momentum": [
                4
            ],
            "exponents": [
                "6.772300E+00",
                "2.319000E+00",
                "7.941000E-01"
            ],
            "coefficients": [
                [
                    "1.000000E+00",
                    "0.000000E+00",
                    "0.000000E+00"
                ],
                [
                    "0.000000E+00",
                    "1.000000E+00",
                    "0.000000E+00"
                ],
                [
                    "0.000000E+00",
                    "0.000000E+00",
                    "1.000000E+00"
                ]
            ]
        },
        {
            "function_type": "gto_spherical",
            "region": "",
            "angular_momentum": [
                5
            ],
            "exponents": [
                "4.951100E+00",
                "1.551300E+00"
            ],
            "coefficients": [
                [
                    "1.000000E+00",
                    "0.000000E+00"
                ],
                [
                    "0.000000E+00",
                    "1.000000E+00"
                ]
            ]
        },
        {
            "function_type": "gto_spherical",
            "region": "",
            "angular_momentum": [
                6
            ],
            "exponents": [
                "3.695000E+00"
            ],
            "coefficients": [
                [
                    "1.0000000"
                ]
            ]
        },
        {
            "function_type": "gto",
            "region": "",
            "angular_momentum": [
                0
            ],
            "exponents": [
                "0.0129000"
            ],
            "coefficients": [
                [
                    "1.0000000"
                ]
            ]
        },
        {
            "function_type": "gto",
            "region": "",
            "angular_momentum": [
                1
            ],
            "exponents": [
                "0.0139000"
            ],
            "coefficients": [
                [
                    "1.0000000"
                ]
            ]
        },
        {
            "function_type": "gto_spherical",
            "region": "",
            "angular_momentum": [
                2
            ],
            "exponents": [
                "0.0214100"
            ],
            "coefficients": [
                [
                    "1.0000000"
                ]
            ]
        },
        {
            "function_type": "gto_spherical",
            "region": "",
            "angular_momentum": [
                3
            ],
            "exponents": [
                "0.1265500"
            ],
            "coefficients": [
                [
                    "1.0000000"
                ]
            ]
        },
        {
            "function_type": "gto_spherical",
            "region": "",
            "angular_momentum": [
                4
            ],
            "exponents": [
                "0.2974800"
            ],
            "coefficients": [
                [
                    "1.0000000"
                ]
            ]
        },
        {
            "function_type": "gto_spherical",
            "region": "",
            "angular_momentum": [
                5
            ],
            "exponents": [
                "0.6387800"
            ],
            "coefficients": [
                [
                    "1.0000000"
                ]
            ]
        },
        {
            "function_type": "gto_spherical",
            "region": "",
            "angular_momentum": [
                6
            ],
            "exponents": [
                "1.7051400"
            ],
            "coefficients": [
                [
                    "1.0000000"
                ]
            ]
        }
    ],
    "references": [
        {
            "reference_description": "The cc-pV5Z basis set",
            "reference_keys": [
                "balabanov2005a"
            ]
        },
        {
            "reference_description": "Augmenting functions for cc-pV5Z",
            "reference_keys": [
                "balabanov2005a"
            ]
        }
    ]
}