{
    "electron_shells": [
        {
            "function_type": "gto",
            "region": "",
            "angular_momentum": [
                0
            ],
            "exponents": [
                "223.8530000",
                "23.0948000",
                "14.6522000",
                "6.5704440",
                "1.5378300",
                "0.6909840",
                "0.1349130",
                "0.0474420"
            ],
            "coefficients": [
                [
                    "0.0008710",
                    "-0.0643070",
                    "0.3013160",
                    "-0.7605240",
                    "0.8940710",
                    "0.4278790",
                    "0.0101880",
                    "-0.0024450"
                ],
                [
                    "-0.0002290",
                    "0.0155940",
                    "-0.0810470",
                    "0.2272510",
                    "-0.3625630",
                    "-0.2507830",
                    "0.6135330",
                    "0.5582600"
                ],
                [
                    "0.0010770",
                    "-0.0716490",
                    "0.2889750",
                    "-0.7315460",
                    "1.9768990",
                    "-1.3519510",
                    "-1.1186740",
                    "1.3026160"
                ],
                [
                    "0.0000000",
                    "0.0000000",
                    "0.0000000",
                    "0.0000000",
                    "0.0000000",
                    "0.0000000",
                    "0.0000000",
                    "1.0000000"
                ]
            ]
        },
        {
            "function_type": "gto",
            "region": "",
            "angular_momentum": [
                1
            ],
            "exponents": [
                "13.7175000",
                "8.4632200",
                "2.1182000",
                "0.9892620",
                "0.4317810",
                "0.1391600",
                "0.0461490"
            ],
            "coefficients": [
                [
                    "0.0776160",
                    "-0.2579430",
                    "0.5352740",
                    "0.4963620",
                    "0.1231090",
                    "0.0032100",
                    "0.0003400"
                ],
                [
                    "-0.0180110",
                    "0.0637170",
                    "-0.1587410",
                    "-0.1762800",
                    "0.0710060",
                    "0.5775860",
                    "0.4994910"
                ],
                [
                    "-0.0307300",
                    "0.1087440",
                    "-0.2782310",
                    "-0.3293900",
                    "0.3546300",
                    "0.7814580",
                    "0.0852520"
                ],
                [
                    "0.0000000",
                    "0.0000000",
                    "0.0000000",
                    "0.0000000",
                    "0.0000000",
                    "0.0000000",
                    "1.0000000"
                ]
            ]
        },
        {
            "function_type": "gto_spherical",
            "region": "",
            "angular_momentum": [
                2
            ],
            "exponents": [
                "31.6697000",
                "12.2214000",
                "3.1219900",
                "1.3894100",
                "0.5732030",
                "0.2117080"
            ],
            "coefficients": [
                [
                    "0.0031630",
                    "-0.0117910",
                    "0.2411940",
                    "0.4489980",
                    "0.3802110",
                    "0.1445530"
                ],
                [
                    "-0.0048710",
                    "0.0185820",
                    "-0.4766730",
                    "-0.4576040",
                    "0.5714620",
                    "0.4973800"
                ],
                [
                    "0.0000000",
                    "0.0000000",
                    "0.0000000",
                    "0.0000000",
                    "0.0000000",
                    "1.0000000"
                ]
            ]
        },
        {
            "function_type": "gto_spherical",
            "region": "",
            "angular_momentum": [
                3
            ],
            "exponents": [
                "1.5393000"
            ],
            "coefficients": [
                [
                    "1.0000000"
                ]
            ]
        }
    ],
    "references": [
        {
            "reference_description": "cc-pVDZ-PP",
            "reference_keys": [
                "peterson2005a"
            ]
        },
        {
            "reference_description": "Stuttgart-Koeln MCDHF RSC ECP",
            "reference_keys": [
                "figgen2005a"
            ]
        }
    ],
    "ecp_potentials": [
        {
            "angular_momentum": [
                4
            ],
            "coefficients": [
                [
                    "0.0000000"
                ]
            ],
            "ecp_type": "scalar_ecp",
            "r_exponents": [
                2
            ],
            "gaussian_exponents": [
                "1.0000000"
            ]
        },
        {
            "angular_momentum": [
                0
            ],
            "coefficients": [
                [
                    "270.0394480",
                    "38.8777660"
                ]
            ],
            "ecp_type": "scalar_ecp",
            "r_exponents": [
                2,
                2
            ],
            "gaussian_exponents": [
                "13.3551760",
                "7.3083780"
            ]
        },
        {
            "angular_momentum": [
                1
            ],
            "coefficients": [
                [
                    "64.6074700",
                    "129.2194450",
                    "10.6225580",
                    "21.2650460"
                ]
            ],
            "ecp_type": "scalar_ecp",
            "r_exponents": [
                2,
                2,
                2,
                2
            ],
            "gaussian_exponents": [
                "12.6597280",
                "12.2896390",
                "6.7861760",
                "6.4007430"
            ]
        },
        {
            "angular_momentum": [
                2
            ],
            "coefficients": [
                [
                    "31.6639650",
                    "47.4892160",
                    "5.1862000",
                    "7.5660630"
                ]
            ],
            "ecp_type": "scalar_ecp",
            "r_exponents": [
                2,
                2,
                2,
                2
            ],
            "gaussian_exponents": [
                "11.1617220",
                "11.2196150",
                "4.5377330",
                "4.3357270"
            ]
        },
        {
            "angular_momentum": [
                3
            ],
            "coefficients": [
                [
                    "-12.6327850",
                    "-16.7601710"
                ]
            ],
            "ecp_type": "scalar_ecp",
            "r_exponents": [
                2,
                2
            ],
            "gaussian_exponents": [
                "11.4789860",
                "11.4870270"
            ]
        }
    ], 
    "ecp_electrons": 28
}