{
    "electron_shells": [
        {
            "function_type": "gto",
            "region": "",
            "angular_momentum": [
                0
            ],
            "exponents": [
                "629.1260000",
                "62.9635000",
                "39.5791000",
                "11.9173000",
                "2.5082400",
                "1.0301900",
                "0.1540020",
                "0.0527950"
            ],
            "coefficients": [
                [
                    "0.0005590",
                    "-0.0096800",
                    "0.0623540",
                    "-0.4148790",
                    "0.7544660",
                    "0.4589960",
                    "0.0116640",
                    "-0.0035630"
                ],
                [
                    "-0.0001210",
                    "0.0014890",
                    "-0.0127370",
                    "0.0972460",
                    "-0.2199170",
                    "-0.2364740",
                    "0.5812910",
                    "0.5541210"
                ],
                [
                    "0.0004210",
                    "-0.0051090",
                    "0.0414470",
                    "-0.3416430",
                    "1.4386170",
                    "-0.9824290",
                    "-1.1876310",
                    "1.3092000"
                ],
                [
                    "0.0000000",
                    "0.0000000",
                    "0.0000000",
                    "0.0000000",
                    "0.0000000",
                    "0.0000000",
                    "0.0000000",
                    "1.0000000"
                ]
            ]
        },
        {
            "function_type": "gto",
            "region": "",
            "angular_momentum": [
                1
            ],
            "exponents": [
                "92.9034000",
                "19.7452000",
                "4.5507300",
                "2.0019000",
                "0.8438790",
                "0.2033810",
                "0.0595720"
            ],
            "coefficients": [
                [
                    "0.0024880",
                    "-0.0791360",
                    "0.3880590",
                    "0.5093540",
                    "0.2245750",
                    "0.0126800",
                    "-0.0019320"
                ],
                [
                    "-0.0004030",
                    "0.0154470",
                    "-0.0843250",
                    "-0.1364890",
                    "0.0008020",
                    "0.5157920",
                    "0.5956560"
                ],
                [
                    "-0.0005300",
                    "0.0247430",
                    "-0.1424780",
                    "-0.2340320",
                    "0.0921870",
                    "0.8377700",
                    "0.1974590"
                ],
                [
                    "0.0000000",
                    "0.0000000",
                    "0.0000000",
                    "0.0000000",
                    "0.0000000",
                    "0.0000000",
                    "1.0000000"
                ]
            ]
        },
        {
            "function_type": "gto_spherical",
            "region": "",
            "angular_momentum": [
                2
            ],
            "exponents": [
                "71.2766000",
                "22.7604000",
                "8.3236900",
                "3.1687500",
                "1.1470300",
                "0.3666430"
            ],
            "coefficients": [
                [
                    "0.0158950",
                    "0.0924540",
                    "0.2594720",
                    "0.4033140",
                    "0.3878340",
                    "0.2022580"
                ],
                [
                    "-0.0225160",
                    "-0.1333030",
                    "-0.3932530",
                    "-0.3512140",
                    "0.4061710",
                    "0.5792050"
                ],
                [
                    "0.0000000",
                    "0.0000000",
                    "0.0000000",
                    "0.0000000",
                    "0.0000000",
                    "1.0000000"
                ]
            ]
        },
        {
            "function_type": "gto_spherical",
            "region": "",
            "angular_momentum": [
                3
            ],
            "exponents": [
                "3.2168000"
            ],
            "coefficients": [
                [
                    "1.0000000"
                ]
            ]
        },
        {
            "function_type": "gto",
            "region": "",
            "angular_momentum": [
                0
            ],
            "exponents": [
                "0.0181000"
            ],
            "coefficients": [
                [
                    "1.0000000"
                ]
            ]
        },
        {
            "function_type": "gto",
            "region": "",
            "angular_momentum": [
                1
            ],
            "exponents": [
                "0.0174000"
            ],
            "coefficients": [
                [
                    "1.0000000"
                ]
            ]
        },
        {
            "function_type": "gto_spherical",
            "region": "",
            "angular_momentum": [
                2
            ],
            "exponents": [
                "0.1172000"
            ],
            "coefficients": [
                [
                    "1.0000000"
                ]
            ]
        },
        {
            "function_type": "gto_spherical",
            "region": "",
            "angular_momentum": [
                3
            ],
            "exponents": [
                "1.0870000"
            ],
            "coefficients": [
                [
                    "1.0000000"
                ]
            ]
        }
    ],
    "references": [
        {
            "reference_description": "cc-pVDZ-PP",
            "reference_keys": [
                "peterson2005a"
            ]
        },
        {
            "reference_description": "aug-cc-pVDZ-PP Diffuse",
            "reference_keys": [
                "peterson2005a"
            ]
        },
        {
            "reference_description": "Stuttgart-Koeln MCDHF RSC ECP",
            "reference_keys": [
                "figgen2005a"
            ]
        }
    ],
    "ecp_potentials": [
        {
            "angular_momentum": [
                4
            ],
            "coefficients": [
                [
                    "0.0000000"
                ]
            ],
            "ecp_type": "scalar_ecp",
            "r_exponents": [
                2
            ],
            "gaussian_exponents": [
                "1.0000000"
            ]
        },
        {
            "angular_momentum": [
                0
            ],
            "coefficients": [
                [
                    "399.9863990",
                    "85.4897500"
                ]
            ],
            "ecp_type": "scalar_ecp",
            "r_exponents": [
                2,
                2
            ],
            "gaussian_exponents": [
                "34.1740010",
                "14.4563710"
            ]
        },
        {
            "angular_momentum": [
                1
            ],
            "coefficients": [
                [
                    "92.3810770",
                    "184.7711760",
                    "23.0025410",
                    "46.0574270"
                ]
            ],
            "ecp_type": "scalar_ecp",
            "r_exponents": [
                2,
                2,
                2,
                2
            ],
            "gaussian_exponents": [
                "39.8886830",
                "39.6550170",
                "15.2905460",
                "14.9035240"
            ]
        },
        {
            "angular_momentum": [
                2
            ],
            "coefficients": [
                [
                    "-13.6907340",
                    "-20.5439800",
                    "-1.3161540",
                    "-1.8387150"
                ]
            ],
            "ecp_type": "scalar_ecp",
            "r_exponents": [
                2,
                2,
                2,
                2
            ],
            "gaussian_exponents": [
                "43.7082960",
                "43.6985360",
                "15.1507180",
                "15.2824410"
            ]
        },
        {
            "angular_momentum": [
                3
            ],
            "coefficients": [
                [
                    "-0.3703600",
                    "-1.0629430"
                ]
            ],
            "ecp_type": "scalar_ecp",
            "r_exponents": [
                2,
                2
            ],
            "gaussian_exponents": [
                "8.1600140",
                "12.2284220"
            ]
        }
    ], 
    "ecp_electrons": 10
}